{"created_at": "Mon Sep 26 21:26:28 +0000 2016", "id": 780518928586072065, "id_str": "780518928586072065", "text": "At Hofstra University for tonight's first presidential #debate https://t.co/4rE3cXHeEY", "truncated": false, "entities": {"hashtags": [{"text": "debate", "indices": [55, 62]}], "symbols": [], "user_mentions": [], "urls": [{"url": "https://t.co/4rE3cXHeEY", "expanded_url": "https://www.instagram.com/p/BK1Yx3MgbcW/", "display_url": "instagram.com/p/BK1Yx3MgbcW/", "indices": [63, 86]}]}, "source": "<a href=\"http://instagram.com\" rel=\"nofollow\">Instagram</a>", "in_reply_to_status_id": null, "in_reply_to_status_id_str": null, "in_reply_to_user_id": null, "in_reply_to_user_id_str": null, "in_reply_to_screen_name": null, "user": {"id": 44397881, "id_str": "44397881", "name": "Kate Snow", "screen_name": "tvkatesnow", "location": "New York, NY", "description": "Anchor @NBCNightlyNews Sunday, Senior National Correspondent @NBCNews. Wife of Chris Bro @chrisbronext Mom of Zack and Abby. Snap & Instagram: TVKateSnow", "url": "https://t.co/SVw2YhvBvt", "entities": {"url": {"urls": [{"url": "https://t.co/SVw2YhvBvt", "expanded_url": "http://nbcnews.com/theDrink", "display_url": "nbcnews.com/theDrink", "indices": [0, 23]}]}, "description": {"urls": []}}, "protected": false, "followers_count": 87093, "friends_count": 673, "listed_count": 1363, "created_at": "Wed Jun 03 16:46:54 +0000 2009", "favourites_count": 48, "utc_offset": null, "time_zone": null, "geo_enabled": true, "verified": true, "statuses_count": 20209, "lang": null, "contributors_enabled": false, "is_translator": false, "is_translation_enabled": false, "profile_background_color": "000000", "profile_background_image_url": "http://abs.twimg.com/images/themes/theme5/bg.gif", "profile_background_image_url_https": "https://abs.twimg.com/images/themes/theme5/bg.gif", "profile_background_tile": false, "profile_image_url": "http://pbs.twimg.com/profile_images/880884831055425539/f7_ypNzl_normal.jpg", "profile_image_url_https": "https://pbs.twimg.com/profile_images/880884831055425539/f7_ypNzl_normal.jpg", "profile_banner_url": "https://pbs.twimg.com/profile_banners/44397881/1487377081", "profile_link_color": "2C62CF", "profile_sidebar_border_color": "FFFFFF", "profile_sidebar_fill_color": "FFFFFF", "profile_text_color": "000000", "profile_use_background_image": true, "has_extended_profile": false, "default_profile": false, "default_profile_image": false, "following": false, "follow_request_sent": false, "notifications": false, "translator_type": "none", "withheld_in_countries": []}, "geo": null, "coordinates": null, "place": null, "contributors": null, "is_quote_status": false, "retweet_count": 0, "favorite_count": 13, "favorited": false, "retweeted": false, "possibly_sensitive": false, "lang": "en"}