{"created_at": "Thu Sep 29 10:53:43 +0000 2016", "id": 781446855037116416, "id_str": "781446855037116416", "text": "FULL Donald Trump vs Hillary Clinton | First Presidential Debate 2016 | Hofstra University\u2026 https://t.co/PW4ZtawEDU https://t.co/AwasrEkuAt", "truncated": false, "entities": {"hashtags": [], "symbols": [], "user_mentions": [], "urls": [{"url": "https://t.co/PW4ZtawEDU", "expanded_url": "http://dlvr.it/MMD1QZ", "display_url": "dlvr.it/MMD1QZ", "indices": [92, 115]}], "media": [{"id": 781446852176601088, "id_str": "781446852176601088", "indices": [116, 139], "media_url": "http://pbs.twimg.com/media/CthBxZLVYAA0l7d.jpg", "media_url_https": "https://pbs.twimg.com/media/CthBxZLVYAA0l7d.jpg", "url": "https://t.co/AwasrEkuAt", "display_url": "pic.twitter.com/AwasrEkuAt", "expanded_url": "https://twitter.com/TVs_LED/status/781446855037116416/photo/1", "type": "photo", "sizes": {"medium": {"w": 480, "h": 360, "resize": "fit"}, "thumb": {"w": 150, "h": 150, "resize": "crop"}, "small": {"w": 480, "h": 360, "resize": "fit"}, "large": {"w": 480, "h": 360, "resize": "fit"}}}]}, "extended_entities": {"media": [{"id": 781446852176601088, "id_str": "781446852176601088", "indices": [116, 139], "media_url": "http://pbs.twimg.com/media/CthBxZLVYAA0l7d.jpg", "media_url_https": "https://pbs.twimg.com/media/CthBxZLVYAA0l7d.jpg", "url": "https://t.co/AwasrEkuAt", "display_url": "pic.twitter.com/AwasrEkuAt", "expanded_url": "https://twitter.com/TVs_LED/status/781446855037116416/photo/1", "type": "photo", "sizes": {"medium": {"w": 480, "h": 360, "resize": "fit"}, "thumb": {"w": 150, "h": 150, "resize": "crop"}, "small": {"w": 480, "h": 360, "resize": "fit"}, "large": {"w": 480, "h": 360, "resize": "fit"}}}]}, "source": "<a href=\"https://dlvrit.com/\" rel=\"nofollow\">dlvr.it</a>", "in_reply_to_status_id": null, "in_reply_to_status_id_str": null, "in_reply_to_user_id": null, "in_reply_to_user_id_str": null, "in_reply_to_screen_name": null, "user": {"id": 3365825139, "id_str": "3365825139", "name": "VM Videos", "screen_name": "VMVideos_com", "location": "", "description": "Videos from many sources without ads.", "url": "https://t.co/b2kuPtCKea", "entities": {"url": {"urls": [{"url": "https://t.co/b2kuPtCKea", "expanded_url": "http://www.vm-videos.com", "display_url": "vm-videos.com", "indices": [0, 23]}]}, "description": {"urls": []}}, "protected": false, "followers_count": 600, "friends_count": 585, "listed_count": 0, "created_at": "Wed Jul 08 12:37:11 +0000 2015", "favourites_count": 66, "utc_offset": null, "time_zone": null, "geo_enabled": true, "verified": false, "statuses_count": 169563, "lang": null, "contributors_enabled": false, "is_translator": false, "is_translation_enabled": false, "profile_background_color": "0099B9", "profile_background_image_url": "http://abs.twimg.com/images/themes/theme4/bg.gif", "profile_background_image_url_https": "https://abs.twimg.com/images/themes/theme4/bg.gif", "profile_background_tile": false, "profile_image_url": "http://pbs.twimg.com/profile_images/824933954314702850/ZsLHBw4B_normal.jpg", "profile_image_url_https": "https://pbs.twimg.com/profile_images/824933954314702850/ZsLHBw4B_normal.jpg", "profile_banner_url": "https://pbs.twimg.com/profile_banners/3365825139/1485514627", "profile_link_color": "0099B9", "profile_sidebar_border_color": "000000", "profile_sidebar_fill_color": "000000", "profile_text_color": "000000", "profile_use_background_image": true, "has_extended_profile": false, "default_profile": false, "default_profile_image": false, "following": false, "follow_request_sent": false, "notifications": false, "translator_type": "none", "withheld_in_countries": []}, "geo": null, "coordinates": null, "place": null, "contributors": null, "is_quote_status": false, "retweet_count": 0, "favorite_count": 0, "favorited": false, "retweeted": false, "possibly_sensitive": false, "lang": "en"}