{"created_at": "Wed Oct 04 22:13:00 +0000 2017", "id": 915701313941499904, "id_str": "915701313941499904", "text": "\ud83d\ude33\nBREAKING: Trump Votes For Death Penalty For Being Gay https://t.co/b391iizosl via @groopspeak", "truncated": false, "entities": {"hashtags": [], "symbols": [], "user_mentions": [], "urls": [{"url": "https://t.co/b391iizosl", "expanded_url": "http://news.groopspeak.com/breaking-trump-votes-for-death-penalty-for-being-gay/", "display_url": "news.groopspeak.com/breaking-trump\u2026", "indices": [56, 79]}]}, "source": "<a href=\"http://twitter.com/#!/download/ipad\" rel=\"nofollow\">Twitter for iPad</a>", "in_reply_to_status_id": null, "in_reply_to_status_id_str": null, "in_reply_to_user_id": null, "in_reply_to_user_id_str": null, "in_reply_to_screen_name": null, "user": {"id": 451708063, "id_str": "451708063", "name": "MaryJoCrawford", "screen_name": "MaryJoMcManus", "location": "Antrim", "description": "", "url": null, "entities": {"description": {"urls": []}}, "protected": false, "followers_count": 729, "friends_count": 437, "listed_count": 37, "created_at": "Sat Dec 31 22:15:19 +0000 2011", "favourites_count": 33923, "utc_offset": null, "time_zone": null, "geo_enabled": true, "verified": false, "statuses_count": 102518, "lang": null, "contributors_enabled": false, "is_translator": false, "is_translation_enabled": false, "profile_background_color": "C0DEED", "profile_background_image_url": "http://abs.twimg.com/images/themes/theme1/bg.png", "profile_background_image_url_https": "https://abs.twimg.com/images/themes/theme1/bg.png", "profile_background_tile": false, "profile_image_url": "http://pbs.twimg.com/profile_images/935818622102130688/24MZBxKv_normal.jpg", "profile_image_url_https": "https://pbs.twimg.com/profile_images/935818622102130688/24MZBxKv_normal.jpg", "profile_banner_url": "https://pbs.twimg.com/profile_banners/451708063/1447795154", "profile_link_color": "1DA1F2", "profile_sidebar_border_color": "C0DEED", "profile_sidebar_fill_color": "DDEEF6", "profile_text_color": "333333", "profile_use_background_image": true, "has_extended_profile": true, "default_profile": true, "default_profile_image": false, "following": false, "follow_request_sent": false, "notifications": false, "translator_type": "none", "withheld_in_countries": []}, "geo": null, "coordinates": null, "place": {"id": "08104612ff4c5274", "url": "https://api.twitter.com/1.1/geo/id/08104612ff4c5274.json", "place_type": "city", "name": "Antrim", "full_name": "Antrim, Northern Ireland", "country_code": "GB", "country": "Reino Unido", "contained_within": [], "bounding_box": {"type": "Polygon", "coordinates": [[[-6.2353295, 54.6993594], [-6.1708269, 54.6993594], [-6.1708269, 54.7392656], [-6.2353295, 54.7392656]]]}, "attributes": {}}, "contributors": null, "is_quote_status": false, "retweet_count": 0, "favorite_count": 0, "favorited": false, "retweeted": false, "possibly_sensitive": false, "lang": "en"}