{"created_at": "Tue Jan 09 03:26:04 +0000 2018", "id": 950569333448585223, "id_str": "950569333448585223", "text": "#Trump Votes For Death Penalty For Being #Gay https://t.co/Pw0sBAmdcL", "truncated": false, "entities": {"hashtags": [{"text": "Trump", "indices": [0, 6]}, {"text": "Gay", "indices": [41, 45]}], "symbols": [], "user_mentions": [], "urls": [{"url": "https://t.co/Pw0sBAmdcL", "expanded_url": "http://news.groopspeak.com/trump-votes-for-death-penalty-for-being-gay-3/", "display_url": "news.groopspeak.com/trump-votes-fo\u2026", "indices": [46, 69]}]}, "source": "<a href=\"http://twitter.com\" rel=\"nofollow\">Twitter Web Client</a>", "in_reply_to_status_id": null, "in_reply_to_status_id_str": null, "in_reply_to_user_id": null, "in_reply_to_user_id_str": null, "in_reply_to_screen_name": null, "user": {"id": 22066415, "id_str": "22066415", "name": "Reda StCyr", "screen_name": "StCyrlyMe2", "location": "Henderson Nv", "description": "36yrs Employed Now Retired United States Postmaster I now spend my time working with, advocating & speaking out 4 voiceless on political issues", "url": "https://t.co/HvMwzxLikO", "entities": {"url": {"urls": [{"url": "https://t.co/HvMwzxLikO", "expanded_url": "http://wefollow.com/StCyrlyMe2", "display_url": "wefollow.com/StCyrlyMe2", "indices": [0, 23]}]}, "description": {"urls": []}}, "protected": false, "followers_count": 15678, "friends_count": 17174, "listed_count": 506, "created_at": "Thu Feb 26 21:41:04 +0000 2009", "favourites_count": 6043, "utc_offset": null, "time_zone": null, "geo_enabled": true, "verified": false, "statuses_count": 223731, "lang": null, "contributors_enabled": false, "is_translator": false, "is_translation_enabled": false, "profile_background_color": "FFFFFF", "profile_background_image_url": "http://abs.twimg.com/images/themes/theme15/bg.png", "profile_background_image_url_https": "https://abs.twimg.com/images/themes/theme15/bg.png", "profile_background_tile": false, "profile_image_url": "http://pbs.twimg.com/profile_images/1351359394/MeNewPick_normal.jpg", "profile_image_url_https": "https://pbs.twimg.com/profile_images/1351359394/MeNewPick_normal.jpg", "profile_link_color": "430291", "profile_sidebar_border_color": "FFFFFF", "profile_sidebar_fill_color": "FFFFFF", "profile_text_color": "000000", "profile_use_background_image": true, "has_extended_profile": true, "default_profile": false, "default_profile_image": false, "following": false, "follow_request_sent": false, "notifications": false, "translator_type": "none", "withheld_in_countries": []}, "geo": null, "coordinates": null, "place": null, "contributors": null, "is_quote_status": false, "retweet_count": 1, "favorite_count": 1, "favorited": false, "retweeted": false, "possibly_sensitive": false, "lang": "en"}