{"created_at": "Mon Aug 29 02:00:49 +0000 2016", "id": 770078722653298692, "id_str": "770078722653298692", "text": "@WendyPeters The first lesser of 2 evils debate is Mon Sept 26, 2016\nFirst presidential debate Hofstra University, Hempstead, NY", "truncated": false, "entities": {"hashtags": [], "symbols": [], "user_mentions": [{"screen_name": "WendyPeters", "name": "Wendy Peters", "id": 25376452, "id_str": "25376452", "indices": [0, 12]}], "urls": []}, "source": "<a href=\"http://twitter.com\" rel=\"nofollow\">Twitter Web Client</a>", "in_reply_to_status_id": 770077248342859776, "in_reply_to_status_id_str": "770077248342859776", "in_reply_to_user_id": 25376452, "in_reply_to_user_id_str": "25376452", "in_reply_to_screen_name": "WendyPeters", "user": {"id": 80155484, "id_str": "80155484", "name": "Arne Zabell", "screen_name": "RuralBC", "location": "British Columbia, Canada", "description": "Committed to helping persons, NGO's and companies navigate the mire we have allowed to be created in our local, provincial and federal governments.", "url": "http://t.co/kOjxzZsKvE", "entities": {"url": {"urls": [{"url": "http://t.co/kOjxzZsKvE", "expanded_url": "http://zabell.homestead.com/", "display_url": "zabell.homestead.com", "indices": [0, 22]}]}, "description": {"urls": []}}, "protected": false, "followers_count": 1388, "friends_count": 1512, "listed_count": 140, "created_at": "Mon Oct 05 23:28:43 +0000 2009", "favourites_count": 12198, "utc_offset": null, "time_zone": null, "geo_enabled": false, "verified": false, "statuses_count": 73935, "lang": null, "contributors_enabled": false, "is_translator": false, "is_translation_enabled": false, "profile_background_color": "BADFCD", "profile_background_image_url": "http://abs.twimg.com/images/themes/theme12/bg.gif", "profile_background_image_url_https": "https://abs.twimg.com/images/themes/theme12/bg.gif", "profile_background_tile": true, "profile_image_url": "http://pbs.twimg.com/profile_images/658664989822054400/WI-eXCyc_normal.jpg", "profile_image_url_https": "https://pbs.twimg.com/profile_images/658664989822054400/WI-eXCyc_normal.jpg", "profile_banner_url": "https://pbs.twimg.com/profile_banners/80155484/1414443537", "profile_link_color": "FF0000", "profile_sidebar_border_color": "000000", "profile_sidebar_fill_color": "FFF7CC", "profile_text_color": "0C3E53", "profile_use_background_image": true, "has_extended_profile": false, "default_profile": false, "default_profile_image": false, "following": false, "follow_request_sent": false, "notifications": false, "translator_type": "none", "withheld_in_countries": []}, "geo": null, "coordinates": null, "place": null, "contributors": null, "is_quote_status": false, "retweet_count": 0, "favorite_count": 1, "favorited": false, "retweeted": false, "lang": "en"}